{"total":153,"page":11,"pageSize":10,"employeeList":[{"id":102,"img":"/img/101.jpg","name":"姓名101","desc":"描述101"},{"id":103,"img":"/img/102.jpg","name":"姓名102","desc":"描述102"},{"id":104,"img":"/img/103.jpg","name":"姓名103","desc":"描述103"},{"id":105,"img":"/img/104.jpg","name":"姓名104","desc":"描述104"},{"id":106,"img":"/img/105.jpg","name":"姓名105","desc":"描述105"},{"id":107,"img":"/img/106.jpg","name":"姓名106","desc":"描述106"},{"id":108,"img":"/img/107.jpg","name":"姓名107","desc":"描述107"},{"id":109,"img":"/img/108.jpg","name":"姓名108","desc":"描述108"},{"id":110,"img":"/img/109.jpg","name":"姓名109","desc":"描述109"},{"id":111,"img":"/img/110.jpg","name":"姓名110","desc":"描述110"}]}